bump.py
bump-1.4.0.dist-info/METADATA
bump-1.4.0.dist-info/WHEEL
bump-1.4.0.dist-info/entry_points.txt
bump-1.4.0.dist-info/top_level.txt
bump-1.4.0.dist-info/RECORD
