Metadata-Version: 2.4
Name: bump
Version: 1.4.0
Summary: Bumps package version numbers
Author-email: Mark Steve Samson <hello@marksteve.com>
Project-URL: Homepage, https://github.com/di/bump
Keywords: bump,increment,package,version
Classifier: Programming Language :: Python :: 3.10
Classifier: Programming Language :: Python :: 3.11
Classifier: Programming Language :: Python :: 3.12
Classifier: License :: OSI Approved :: MIT License
Requires-Python: >=3.10
Requires-Dist: click<9,>=6
Requires-Dist: first
Requires-Dist: packaging>=17.1
Requires-Dist: toml
Provides-Extra: dev
Requires-Dist: pytest; extra == "dev"
Requires-Dist: black; extra == "dev"
Requires-Dist: build; extra == "dev"
Requires-Dist: twine; extra == "dev"
